jpsy/__init__.py
jpsy/jpsy.py
jpsy-0.1.2.dist-info/LICENSE
jpsy-0.1.2.dist-info/METADATA
jpsy-0.1.2.dist-info/WHEEL
jpsy-0.1.2.dist-info/top_level.txt
jpsy-0.1.2.dist-info/RECORD
