Metadata-Version: 2.1
Name: jpsy
Version: 0.1.2
Summary: Enforcing Language Naming Conventions
Home-page: https://github.com/RomAviad/jpsy
Author: Aviad Rom
License: UNKNOWN
Platform: UNKNOWN
Classifier: Programming Language :: Python
Classifier: License :: OSI Approved :: MIT License
Classifier: Operating System :: OS Independent
Classifier: Intended Audience :: Developers
Classifier: Development Status :: 4 - Beta
